setup.py
pi_app/__init__.py
pi_app/pi_app.py
pi_app.egg-info/PKG-INFO
pi_app.egg-info/SOURCES.txt
pi_app.egg-info/dependency_links.txt
pi_app.egg-info/requires.txt
pi_app.egg-info/top_level.txt