Metadata-Version: 1.1
Name: pi-app
Version: 0.0.1
Summary: A simple yet powerful tool for developing menu based apps
Home-page: https://github.com/rodrigodiez/PiApp
Author: Rodrigo Diez Villamuera
Author-email: rodrigo@rodrigodiez.io
License: UNKNOWN
Download-URL: https://github.com/rodrigodiez/PiApp/archive/0.0.1.tar.gz
Platform: UNKNOWN
Classifier: Development Status :: 3 - Alpha
Classifier: Environment :: Console
Classifier: Intended Audience :: Developers
Classifier: License :: OSI Approved :: MIT License
Classifier: Natural Language :: English
Classifier: Operating System :: OS Independent
Classifier: Programming Language :: Python :: 2.7
Classifier: Topic :: Software Development
